Acquisition/Acquisition.h
Acquisition/_Acquisition.c
Acquisition/_Acquisition.cpython-314-x86_64-linux-gnu.so
Acquisition/__init__.py
Acquisition/interfaces.py
Acquisition/tests.py
acquisition-6.2.dist-info/METADATA
acquisition-6.2.dist-info/WHEEL
acquisition-6.2.dist-info/top_level.txt
acquisition-6.2.dist-info/RECORD
acquisition-6.2.dist-info/licenses/LICENSE.txt
