Metadata-Version: 2.4
Name: Acquisition
Version: 6.2
Summary: Acquisition is a mechanism that allows objects to obtain attributes from the containment hierarchy they're in.
Author-email: Zope Foundation and contributors <zope-dev@zope.dev>
Maintainer-email: Plone Foundation and contributors <zope-dev@zope.dev>
License-Expression: ZPL-2.1
Project-URL: Issues, https://github.com/zopefoundation/Acquisition/issues
Project-URL: Source, https://github.com/zopefoundation/Acquisition
Project-URL: Changelog, https://github.com/zopefoundation/Acquisition/blob/master/CHANGES.rst
Classifier: Development Status :: 6 - Mature
Classifier: Environment :: Web Environment
Classifier: Framework :: Zope
Classifier: Framework :: Zope :: 5
Classifier: Operating System :: OS Independent
Classifier: Programming Language :: Python
Classifier: Programming Language :: Python :: 3
Classifier: Programming Language :: Python :: 3 :: Only
Classifier: Programming Language :: Python :: 3.10
Classifier: Programming Language :: Python :: 3.11
Classifier: Programming Language :: Python :: 3.12
Classifier: Programming Language :: Python :: 3.13
Classifier: Programming Language :: Python :: 3.14
Classifier: Programming Language :: Python :: Implementation :: CPython
Classifier: Programming Language :: Python :: Implementation :: PyPy
Requires-Python: >=3.10
License-File: LICENSE.txt
Requires-Dist: ExtensionClass>=4.2.0
Requires-Dist: zope.interface
Provides-Extra: test
Requires-Dist: zope.testrunner; extra == "test"
Dynamic: license-file
